{"ts_ts-typetools.md":"HpkQGdPa","html_index.md":"C65nIj0b","js_js-array.md":"BDrKVszV","sass_index.md":"DzjDVRSm","react_react-class.md":"DszB5m10","designpatterns_adaptermode.md":"B2eTqsz4","index.md":"DU2tujE8","react_react-interview.md":"Cv0xtoEk","ts_ts.md":"Bnn2fr0F","api-examples.md":"CtSYLtXu","vue_vue.md":"C_eGKqkc","vue_vue2.md":"DpDADDna","react_react-zustand.md":"BY0vkocZ","js_js-for-in.md":"DoMvTHO4","designpatterns_decoratormode.md":"C9SD3wlC","js_js-string.md":"CbVg7Au0","ts_ts-basis.md":"BUHZc5_r","designpatterns_constructormode.md":"CiOKnGAu","js_js-map.md":"Aa5RbFhf","interview_index.md":"j6EqZc13","react_react-mobx.md":"BxQ2HSkE","designpatterns_strategymode.md":"BaikLHhY","designpatterns_observermode.md":"BAwFsWmt","js_js-set.md":"C0mRR3kn","react_react-redux-toolkit.md":"D6EiZ8FG","designpatterns_proxymode.md":"BjGUN8U2","markdown-examples.md":"7N0QnGyY","js_js-proxy-reflect.md":"PK_Nmrlp","vue3_vue3-customref.md":"d5UsjuKT","designpatterns_publishsubscribemode.md":"BtvAYo3o","js_js-iterator.md":"nqfOY2Kh","js_js-symbol.md":"CutbSMyj","react_react-hook.md":"BSI4dQqX","designpatterns_responsibilitychainmode.md":"CYa25PRu","designpatterns_modulemode.md":"7hOo6nh2","css_index.md":"DLT8sNfa","designpatterns_prototypemode.md":"DFNvPNYZ","designpatterns_singletonmode.md":"imQ2Cdh5","js_js-object.md":"CsztaQk4","js_js.md":"DqAdny3r","vue3_pinia.md":"lV7NybVi","vue3_vue3.md":"DjJ8H1P_"}
